gpt_translate/__init__.py
gpt_translate/cli.py
gpt_translate/configs.py
gpt_translate/evaluate.py
gpt_translate/loader.py
gpt_translate/prompts.py
gpt_translate/translate.py
gpt_translate/utils.py
gpt_translate/version.py
gpt_translate-6.0.0.dist-info/METADATA
gpt_translate-6.0.0.dist-info/WHEEL
gpt_translate-6.0.0.dist-info/entry_points.txt
gpt_translate-6.0.0.dist-info/licenses/LICENSE
gpt_translate-6.0.0.dist-info/RECORD
