Metadata-Version: 2.4
Name: gpt_translate
Version: 6.0.0
Summary: A tool to translate markdown files using GPT-4
Project-URL: homepage, https://github.com/tcapelle/gpt_translate
Author-email: Thomas Capelle <tcapelle@pm.me>
License: MIT License
License-File: LICENSE
Keywords: artificial intelligence,generative models,natural language processing,openai
Classifier: Development Status :: 4 - Beta
Classifier: Intended Audience :: Developers
Classifier: License :: OSI Approved :: MIT License
Classifier: Programming Language :: Python :: 3.10
Classifier: Topic :: Scientific/Engineering :: Artificial Intelligence
Requires-Python: >=3.9
Requires-Dist: fastcore>=1.5.29
Requires-Dist: litellm>1.50
Requires-Dist: openai>=1.0
Requires-Dist: rich>=13.0
Requires-Dist: simple-parsing>=0.1.5
Requires-Dist: tiktoken>=0.5
Requires-Dist: weave>=0.50.3
